sacpy/EOF.py
sacpy/Filter.py
sacpy/LinReg.py
sacpy/Map.py
sacpy/SVD.py
sacpy/SigTest.py
sacpy/Util.py
sacpy/XrPlot.py
sacpy/XrTools.py
sacpy/__init__.py
sacpy/linger_cal.py
sacpy/load_sst.py
sacpy/repr_html.py
sacpy/settings.py
sacpy/spectral.py
sacpy/version.py
sacpy/data/example/HadISST_sst_5x5.nc
sacpy/data/example/NCEP_wind10m_5x5.nc
sacpy-0.0.24.dist-info/METADATA
sacpy-0.0.24.dist-info/WHEEL
sacpy-0.0.24.dist-info/top_level.txt
sacpy-0.0.24.dist-info/RECORD
