Metadata-Version: 2.1
Name: sacpy
Version: 0.0.24
Summary: A repaid Statistical Analysis tool for Climate or Meteorology data.
Home-page: https://github.com/ZiluM/sacpy
Author: Zilu Meng
Author-email: zilumeng@uw.edu
License: MIT
Keywords: meteorology data statistic climate
Requires-Dist: numpy
Requires-Dist: scipy
Requires-Dist: xarray
